COPYING
ChangeLog
MANIFEST.in
README
setup.py
./__init__.py
./__pkginfo__.py
./hmi/__init__.py
./hmi/console.py
./lib/__init__.py
./lib/archives.py
./lib/create.py
./lib/delete.py
./lib/migrate.py
./lib/restore.py
./lib/resume.py
./lib/save.py
./lib/show.py
./lib/start.py
./lib/stop.py
./lib/suspend.py
./lib/test/__init__.py
./lib/test/clear.py
./lib/test/init.py
./lib/test/unittest_create.py
./lib/test/unittest_save_restore.py
./lib/test/unittest_show.py
./lib/test/unittest_start.py
./lib/test/unittest_stop.py
./lib/test/unittest_suspend_resume.py
bin/logilab-vm
bin/logilab-vm-archives
bin/logilab-vm-create
bin/logilab-vm-delete
bin/logilab-vm-migrate
bin/logilab-vm-restore
bin/logilab-vm-resume
bin/logilab-vm-save
bin/logilab-vm-show
bin/logilab-vm-start
bin/logilab-vm-stop
bin/logilab-vm-suspend
conf/settings.ini
doc/dummy.sh
doc/find_mac_address.py
doc/gen_mac.pl
doc/logilab-vm-archives.1
doc/logilab-vm-create.1
doc/logilab-vm-delete.1
doc/logilab-vm-migrate.1
doc/logilab-vm-restore.1
doc/logilab-vm-resume.1
doc/logilab-vm-save.1
doc/logilab-vm-show.1
doc/logilab-vm-start.1
doc/logilab-vm-stop.1
doc/logilab-vm-suspend.1
doc/logilab-vm.1
hmi/__init__.py
hmi/__init__.pyc
hmi/console.py
hmi/console.pyc
hmi/web/httpd
hmi/web/style.css
hmi/web/cgi-bin/create.py
hmi/web/cgi-bin/functions.py
hmi/web/cgi-bin/index.py
hmi/web/cgi-bin/migrate.py
hmi/web/cgi-bin/restore.py
hmi/web/cgi-bin/save.py
hooks/example.py
hooks/example.sh
hooks/openvz_migrate.sh
lib/test/101.xml
lib/test/102.xml
lib/test/kvm01.xml
lib/test/kvm02.xml
logilab_vm.egg-info/PKG-INFO
logilab_vm.egg-info/SOURCES.txt
logilab_vm.egg-info/dependency_links.txt
logilab_vm.egg-info/top_level.txt
scripts/openvz_dev.sh
scripts/openvz_failure.sh
scripts/openvz_net.sh
scripts/openvz_other.sh
scripts/openvz_post.sh
scripts/openvz_pre.sh
scripts/openvz_sys.sh
scripts/qemu_dev.sh
scripts/qemu_failure.sh
scripts/qemu_net.sh
scripts/qemu_other.sh
scripts/qemu_post.sh
scripts/qemu_pre.sh
scripts/qemu_sys.sh
scripts/echo/openvz_dev.sh
scripts/echo/openvz_failure.sh
scripts/echo/openvz_net.sh
scripts/echo/openvz_other.sh
scripts/echo/openvz_post.sh
