Metadata-Version: 1.0
Name: logilab-vm
Version: 0.2.0
Summary: useful miscellaneous modules used by Logilab projects
Home-page: http://www.logilab.org/project/logilab-vm
Author: Logilab
Author-email: devel@logilab.fr
License: GPL
Platform: UNKNOWN
